docs_assist/__init__.py
docs_assist/main.py
docs_assist-1.1.4.dist-info/METADATA
docs_assist-1.1.4.dist-info/WHEEL
docs_assist-1.1.4.dist-info/top_level.txt
docs_assist-1.1.4.dist-info/RECORD
