Metadata-Version: 2.1
Name: docs-assist
Version: 1.1.4
Summary: An Assistant API based on OpenAI Modern Assistant API. It accepts a document and answer the questions based on the document uploaded.
Author: Muhammad Asif Ali
Requires-Dist: openai
